{"cameraMode":{"drawMode":0,"name":"Shaded","section":"Shading Mode"},"sceneLighting":true,"audioPlay":false,"sceneViewState":{"m_AlwaysRefresh":false,"showFog":true,"showSkybox":true,"showFlares":true,"showImageEffects":true,"showParticleSystems":true,"showVisualEffectGraphs":true,"m_FxEnabled":true},"in2DMode":false,"pivot":{"x":0.4177808463573456,"y":0.7629688382148743,"z":1.006729006767273},"rotation":{"x":-0.0009473592508584261,"y":-0.9980618953704834,"z":-0.016165703535079957,"w":0.059679437428712848},"size":0.7052571177482605,"orthographic":false}